firestore_ci/__init__.py
firestore_ci/firestore_ci.py
firestore_ci-2024.8.24.dist-info/LICENSE
firestore_ci-2024.8.24.dist-info/METADATA
firestore_ci-2024.8.24.dist-info/WHEEL
firestore_ci-2024.8.24.dist-info/top_level.txt
firestore_ci-2024.8.24.dist-info/RECORD
