Metadata-Version: 2.1
Name: firestore-ci
Version: 2024.8.24
Summary: ORM for Firestore with cascade
Home-page: https://github.com/crazynayan/firestore
Author: Nayan Zaveri
Author-email: nayan@crazyideas.co.in
License: MIT
Keywords: firestore google orm cascade
Classifier: Intended Audience :: Developers
Classifier: Topic :: Software Development :: Build Tools
Classifier: License :: OSI Approved :: MIT License
Classifier: Programming Language :: Python :: 3.7
Requires-Python: >=3.5
License-File: LICENSE
Requires-Dist: google-cloud-firestore
